mmts/__init__.py
mmts/scripts/__init__.py
mmts/scripts/deDosfuscation.py
mmts/scripts/parseLnk.py
mmts-0.0.2.dist-info/LICENSE
mmts-0.0.2.dist-info/METADATA
mmts-0.0.2.dist-info/WHEEL
mmts-0.0.2.dist-info/entry_points.txt
mmts-0.0.2.dist-info/top_level.txt
mmts-0.0.2.dist-info/RECORD
