Metadata-Version: 2.1
Name: mmts
Version: 0.0.2
Summary: MM tools script
Home-page: https://github.com/a232319779/mmts
Author: ddvv
Author-email: dadavivi512@gmail.com
License: MIT
Platform: UNKNOWN
Classifier: Programming Language :: Python :: 3
Classifier: License :: OSI Approved :: MIT License
Classifier: Operating System :: OS Independent
Classifier: Programming Language :: Python :: Implementation :: PyPy
Classifier: Topic :: Software Development :: Libraries :: Python Modules
Requires-Python: >=3
License-File: LICENSE
